[
	{
		"seatName": "E10",
		"REGISTRANTSINFO": [{}],
		"PAID": true
	},
	{
		"seatName": "E11",
		"REGISTRANTSINFO": [{}],
		"PAID": false
	},
	{
		"seatName": "E12",
		"REGISTRANTSINFO": [{}],
		"PAID": true
	},
	{
		"seatName": "E13",
		"REGISTRANTSINFO": [{}],
		"PAID": false
	},
	{
		"seatName": "E14",
		"REGISTRANTSINFO": [{}],
		"PAID": true
	},
	{
		"seatName": "E15",
		"REGISTRANTSINFO": [{}],
		"PAID": false
	},
	{
		"seatName": "E16",
		"REGISTRANTSINFO": [{}],
		"PAID": true
	},
	{
		"seatName": "E17",
		"REGISTRANTSINFO": [{}],
		"PAID": true
	},
	{
		"seatName": "E18",
		"REGISTRANTSINFO": [{}],
		"PAID": false
	},
	{
		"seatName": "E19",
		"REGISTRANTSINFO": [{}],
		"PAID": false
	},
	{
		"seatName": "E20",
		"REGISTRANTSINFO": [{}],
		"PAID": false
	},
	{
		"seatName": "E21",
		"REGISTRANTSINFO": [{}],
		"PAID": true
	},
	{
		"seatName": "E22",
		"REGISTRANTSINFO": [{}],
		"PAID": true
	},
	{
		"seatName": "E23",
		"REGISTRANTSINFO": [{}],
		"PAID": false
	},
	{
		"seatName": "E24",
		"REGISTRANTSINFO": [{}],
		"PAID": false
	},
	{
		"seatName": "E25",
		"REGISTRANTSINFO": [{}],
		"PAID": false
	},
	{
		"seatName": "E26",
		"REGISTRANTSINFO": [{}],
		"PAID": true
	},
	{
		"seatName": "E27",
		"REGISTRANTSINFO": [{}],
		"PAID": true
	},
	{
		"seatName": "E28",
		"REGISTRANTSINFO": [{}],
		"PAID": false
	},
	{
		"seatName": "E29",
		"REGISTRANTSINFO": [{}],
		"PAID": true
	},
	{
		"seatName": "E30",
		"REGISTRANTSINFO": [{}],
		"PAID": true
	},
	{
		"seatName": "E31",
		"REGISTRANTSINFO": [{}],
		"PAID": true
	},
	{
		"seatName": "E32",
		"REGISTRANTSINFO": [{}],
		"PAID": true
	},
	{
		"seatName": "E33",
		"REGISTRANTSINFO": [{}],
		"PAID": true
	},
	{
		"seatName": "E34",
		"REGISTRANTSINFO": [{}],
		"PAID": false
	},
	{
		"seatName": "E35",
		"REGISTRANTSINFO": [{}],
		"PAID": true
	},
	{
		"seatName": "E36",
		"REGISTRANTSINFO": [{}],
		"PAID": true
	},
	{
		"seatName": "E37",
		"REGISTRANTSINFO": [{}],
		"PAID": false
	},
	{
		"seatName": "E38",
		"REGISTRANTSINFO": [{}],
		"PAID": true
	},
	{
		"seatName": "E39",
		"REGISTRANTSINFO": [{}],
		"PAID": false
	},
	{
		"seatName": "E40",
		"REGISTRANTSINFO": [{}],
		"PAID": false
	},
	{
		"seatName": "E41",
		"REGISTRANTSINFO": [{}],
		"PAID": true
	},
	{
		"seatName": "E42",
		"REGISTRANTSINFO": [{}],
		"PAID": true
	},
	{
		"seatName": "E43",
		"REGISTRANTSINFO": [{}],
		"PAID": false
	},
	{
		"seatName": "E44",
		"REGISTRANTSINFO": [{}],
		"PAID": true
	},
	{
		"seatName": "E45",
		"REGISTRANTSINFO": [{}],
		"PAID": false
	},
	{
		"seatName": "E46",
		"REGISTRANTSINFO": [{}],
		"PAID": true
	},
	{
		"seatName": "E47",
		"REGISTRANTSINFO": [{}],
		"PAID": true
	},
	{
		"seatName": "E48",
		"REGISTRANTSINFO": [{}],
		"PAID": true
	},
	{
		"seatName": "E49",
		"REGISTRANTSINFO": [{}],
		"PAID": true
	},
	{
		"seatName": "E50",
		"REGISTRANTSINFO": [{}],
		"PAID": true
	},
	{
		"seatName": "F10",
		"REGISTRANTSINFO": [{}],
		"PAID": true
	},
	{
		"seatName": "F11",
		"REGISTRANTSINFO": [{}],
		"PAID": true
	},
	{
		"seatName": "F12",
		"REGISTRANTSINFO": [{}],
		"PAID": true
	},
	{
		"seatName": "F13",
		"REGISTRANTSINFO": [{}],
		"PAID": false
	},
	{
		"seatName": "F14",
		"REGISTRANTSINFO": [{}],
		"PAID": false
	},
	{
		"seatName": "F15",
		"REGISTRANTSINFO": [{}],
		"PAID": false
	},
	{
		"seatName": "F16",
		"REGISTRANTSINFO": [{}],
		"PAID": true
	},
	{
		"seatName": "F17",
		"REGISTRANTSINFO": [{}],
		"PAID": false
	},
	{
		"seatName": "F18",
		"REGISTRANTSINFO": [{}],
		"PAID": true
	},
	{
		"seatName": "F19",
		"REGISTRANTSINFO": [{}],
		"PAID": false
	},
	{
		"seatName": "F20",
		"REGISTRANTSINFO": [{}],
		"PAID": false
	},
	{
		"seatName": "F21",
		"REGISTRANTSINFO": [{}],
		"PAID": false
	},
	{
		"seatName": "F22",
		"REGISTRANTSINFO": [{}],
		"PAID": true
	},
	{
		"seatName": "F23",
		"REGISTRANTSINFO": [{}],
		"PAID": true
	},
	{
		"seatName": "F24",
		"REGISTRANTSINFO": [{}],
		"PAID": true
	},
	{
		"seatName": "F25",
		"REGISTRANTSINFO": [{}],
		"PAID": true
	},
	{
		"seatName": "F26",
		"REGISTRANTSINFO": [{}],
		"PAID": true
	},
	{
		"seatName": "F27",
		"REGISTRANTSINFO": [{}],
		"PAID": true
	},
	{
		"seatName": "F28",
		"REGISTRANTSINFO": [{}],
		"PAID": false
	},
	{
		"seatName": "F29",
		"REGISTRANTSINFO": [{}],
		"PAID": false
	},
	{
		"seatName": "F30",
		"REGISTRANTSINFO": [{}],
		"PAID": true
	},
	{
		"seatName": "F31",
		"REGISTRANTSINFO": [{}],
		"PAID": false
	},
	{
		"seatName": "F32",
		"REGISTRANTSINFO": [{}],
		"PAID": false
	},
	{
		"seatName": "F33",
		"REGISTRANTSINFO": [{}],
		"PAID": false
	},
	{
		"seatName": "F34",
		"REGISTRANTSINFO": [{}],
		"PAID": true
	},
	{
		"seatName": "F35",
		"REGISTRANTSINFO": [{}],
		"PAID": true
	},
	{
		"seatName": "F36",
		"REGISTRANTSINFO": [{}],
		"PAID": false
	},
	{
		"seatName": "F37",
		"REGISTRANTSINFO": [{}],
		"PAID": true
	},
	{
		"seatName": "F38",
		"REGISTRANTSINFO": [{}],
		"PAID": false
	},
	{
		"seatName": "F39",
		"REGISTRANTSINFO": [{}],
		"PAID": true
	},
	{
		"seatName": "F40",
		"REGISTRANTSINFO": [{}],
		"PAID": false
	},
	{
		"seatName": "F41",
		"REGISTRANTSINFO": [{}],
		"PAID": true
	},
	{
		"seatName": "F42",
		"REGISTRANTSINFO": [{}],
		"PAID": true
	},
	{
		"seatName": "F43",
		"REGISTRANTSINFO": [{}],
		"PAID": false
	},
	{
		"seatName": "F44",
		"REGISTRANTSINFO": [{}],
		"PAID": true
	},
	{
		"seatName": "F45",
		"REGISTRANTSINFO": [{}],
		"PAID": true
	},
	{
		"seatName": "F46",
		"REGISTRANTSINFO": [{}],
		"PAID": true
	},
	{
		"seatName": "F47",
		"REGISTRANTSINFO": [{}],
		"PAID": true
	},
	{
		"seatName": "F48",
		"REGISTRANTSINFO": [{}],
		"PAID": true
	},
	{
		"seatName": "F49",
		"REGISTRANTSINFO": [{}],
		"PAID": false
	},
	{
		"seatName": "F50",
		"REGISTRANTSINFO": [{}],
		"PAID": false
	},
	{
		"seatName": "G10",
		"REGISTRANTSINFO": [{}],
		"PAID": false
	},
	{
		"seatName": "G11",
		"REGISTRANTSINFO": [{}],
		"PAID": true
	},
	{
		"seatName": "G12",
		"REGISTRANTSINFO": [{}],
		"PAID": true
	},
	{
		"seatName": "G13",
		"REGISTRANTSINFO": [{}],
		"PAID": false
	},
	{
		"seatName": "G14",
		"REGISTRANTSINFO": [{}],
		"PAID": false
	},
	{
		"seatName": "G15",
		"REGISTRANTSINFO": [{}],
		"PAID": false
	},
	{
		"seatName": "G16",
		"REGISTRANTSINFO": [{}],
		"PAID": false
	},
	{
		"seatName": "G17",
		"REGISTRANTSINFO": [{}],
		"PAID": false
	},
	{
		"seatName": "G18",
		"REGISTRANTSINFO": [{}],
		"PAID": true
	},
	{
		"seatName": "G19",
		"REGISTRANTSINFO": [{}],
		"PAID": true
	},
	{
		"seatName": "G20",
		"REGISTRANTSINFO": [{}],
		"PAID": true
	},
	{
		"seatName": "G21",
		"REGISTRANTSINFO": [{}],
		"PAID": false
	},
	{
		"seatName": "G22",
		"REGISTRANTSINFO": [{}],
		"PAID": true
	},
	{
		"seatName": "G23",
		"REGISTRANTSINFO": [{}],
		"PAID": true
	},
	{
		"seatName": "G24",
		"REGISTRANTSINFO": [{}],
		"PAID": true
	},
	{
		"seatName": "G25",
		"REGISTRANTSINFO": [{}],
		"PAID": false
	},
	{
		"seatName": "G26",
		"REGISTRANTSINFO": [{}],
		"PAID": true
	},
	{
		"seatName": "G27",
		"REGISTRANTSINFO": [{}],
		"PAID": false
	},
	{
		"seatName": "G28",
		"REGISTRANTSINFO": [{}],
		"PAID": false
	},
	{
		"seatName": "G29",
		"REGISTRANTSINFO": [{}],
		"PAID": true
	},
	{
		"seatName": "G30",
		"REGISTRANTSINFO": [{}],
		"PAID": true
	},
	{
		"seatName": "G31",
		"REGISTRANTSINFO": [{}],
		"PAID": true
	},
	{
		"seatName": "G32",
		"REGISTRANTSINFO": [{}],
		"PAID": true
	},
	{
		"seatName": "G33",
		"REGISTRANTSINFO": [{}],
		"PAID": false
	},
	{
		"seatName": "G34",
		"REGISTRANTSINFO": [{}],
		"PAID": false
	},
	{
		"seatName": "G35",
		"REGISTRANTSINFO": [{}],
		"PAID": true
	},
	{
		"seatName": "G36",
		"REGISTRANTSINFO": [{}],
		"PAID": true
	},
	{
		"seatName": "G37",
		"REGISTRANTSINFO": [{}],
		"PAID": true
	},
	{
		"seatName": "G38",
		"REGISTRANTSINFO": [{}],
		"PAID": true
	},
	{
		"seatName": "G39",
		"REGISTRANTSINFO": [{}],
		"PAID": true
	},
	{
		"seatName": "G40",
		"REGISTRANTSINFO": [{}],
		"PAID": true
	},
	{
		"seatName": "G41",
		"REGISTRANTSINFO": [{}],
		"PAID": false
	},
	{
		"seatName": "G42",
		"REGISTRANTSINFO": [{}],
		"PAID": true
	},
	{
		"seatName": "G43",
		"REGISTRANTSINFO": [{}],
		"PAID": true
	},
	{
		"seatName": "G44",
		"REGISTRANTSINFO": [{}],
		"PAID": false
	},
	{
		"seatName": "G45",
		"REGISTRANTSINFO": [{}],
		"PAID": true
	},
	{
		"seatName": "G46",
		"REGISTRANTSINFO": [{}],
		"PAID": false
	},
	{
		"seatName": "G47",
		"REGISTRANTSINFO": [{}],
		"PAID": true
	},
	{
		"seatName": "G48",
		"REGISTRANTSINFO": [{}],
		"PAID": true
	},
	{
		"seatName": "G49",
		"REGISTRANTSINFO": [{}],
		"PAID": true
	},
	{
		"seatName": "G50",
		"REGISTRANTSINFO": [{}],
		"PAID": true
	},
	{
		"seatName": "H10",
		"REGISTRANTSINFO": [{}],
		"PAID": true
	},
	{
		"seatName": "H11",
		"REGISTRANTSINFO": [{}],
		"PAID": false
	},
	{
		"seatName": "H12",
		"REGISTRANTSINFO": [{}],
		"PAID": true
	},
	{
		"seatName": "H13",
		"REGISTRANTSINFO": [{}],
		"PAID": true
	},
	{
		"seatName": "H14",
		"REGISTRANTSINFO": [{}],
		"PAID": true
	},
	{
		"seatName": "H15",
		"REGISTRANTSINFO": [{}],
		"PAID": false
	},
	{
		"seatName": "H16",
		"REGISTRANTSINFO": [{}],
		"PAID": false
	},
	{
		"seatName": "H17",
		"REGISTRANTSINFO": [{}],
		"PAID": true
	},
	{
		"seatName": "H18",
		"REGISTRANTSINFO": [{}],
		"PAID": true
	},
	{
		"seatName": "H19",
		"REGISTRANTSINFO": [{}],
		"PAID": false
	},
	{
		"seatName": "H20",
		"REGISTRANTSINFO": [{}],
		"PAID": true
	},
	{
		"seatName": "H21",
		"REGISTRANTSINFO": [{}],
		"PAID": false
	},
	{
		"seatName": "H22",
		"REGISTRANTSINFO": [{}],
		"PAID": true
	},
	{
		"seatName": "H23",
		"REGISTRANTSINFO": [{}],
		"PAID": false
	},
	{
		"seatName": "H24",
		"REGISTRANTSINFO": [{}],
		"PAID": true
	},
	{
		"seatName": "H25",
		"REGISTRANTSINFO": [{}],
		"PAID": true
	},
	{
		"seatName": "H26",
		"REGISTRANTSINFO": [{}],
		"PAID": true
	},
	{
		"seatName": "H27",
		"REGISTRANTSINFO": [{}],
		"PAID": false
	},
	{
		"seatName": "H28",
		"REGISTRANTSINFO": [{}],
		"PAID": false
	},
	{
		"seatName": "H29",
		"REGISTRANTSINFO": [{}],
		"PAID": true
	},
	{
		"seatName": "H30",
		"REGISTRANTSINFO": [{}],
		"PAID": false
	},
	{
		"seatName": "H31",
		"REGISTRANTSINFO": [{}],
		"PAID": true
	},
	{
		"seatName": "H32",
		"REGISTRANTSINFO": [{}],
		"PAID": true
	},
	{
		"seatName": "H33",
		"REGISTRANTSINFO": [{}],
		"PAID": false
	},
	{
		"seatName": "H34",
		"REGISTRANTSINFO": [{}],
		"PAID": false
	},
	{
		"seatName": "H35",
		"REGISTRANTSINFO": [{}],
		"PAID": false
	},
	{
		"seatName": "H36",
		"REGISTRANTSINFO": [{}],
		"PAID": false
	},
	{
		"seatName": "H37",
		"REGISTRANTSINFO": [{}],
		"PAID": true
	},
	{
		"seatName": "H38",
		"REGISTRANTSINFO": [{}],
		"PAID": false
	},
	{
		"seatName": "H39",
		"REGISTRANTSINFO": [{}],
		"PAID": true
	},
	{
		"seatName": "H40",
		"REGISTRANTSINFO": [{}],
		"PAID": true
	},
	{
		"seatName": "H41",
		"REGISTRANTSINFO": [{}],
		"PAID": true
	},
	{
		"seatName": "H42",
		"REGISTRANTSINFO": [{}],
		"PAID": true
	},
	{
		"seatName": "H43",
		"REGISTRANTSINFO": [{}],
		"PAID": false
	},
	{
		"seatName": "H44",
		"REGISTRANTSINFO": [{}],
		"PAID": true
	},
	{
		"seatName": "H45",
		"REGISTRANTSINFO": [{}],
		"PAID": false
	},
	{
		"seatName": "H46",
		"REGISTRANTSINFO": [{}],
		"PAID": false
	},
	{
		"seatName": "H47",
		"REGISTRANTSINFO": [{}],
		"PAID": true
	},
	{
		"seatName": "H48",
		"REGISTRANTSINFO": [{}],
		"PAID": true
	},
	{
		"seatName": "H49",
		"REGISTRANTSINFO": [{}],
		"PAID": false
	},
	{
		"seatName": "H50",
		"REGISTRANTSINFO": [{}],
		"PAID": false
	},
	{
		"seatName": "I10",
		"REGISTRANTSINFO": [{}],
		"PAID": false
	},
	{
		"seatName": "I11",
		"REGISTRANTSINFO": [{}],
		"PAID": false
	},
	{
		"seatName": "I12",
		"REGISTRANTSINFO": [{}],
		"PAID": false
	},
	{
		"seatName": "I13",
		"REGISTRANTSINFO": [{}],
		"PAID": true
	},
	{
		"seatName": "I14",
		"REGISTRANTSINFO": [{}],
		"PAID": false
	},
	{
		"seatName": "I15",
		"REGISTRANTSINFO": [{}],
		"PAID": false
	},
	{
		"seatName": "I16",
		"REGISTRANTSINFO": [{}],
		"PAID": false
	},
	{
		"seatName": "I17",
		"REGISTRANTSINFO": [{}],
		"PAID": false
	},
	{
		"seatName": "I18",
		"REGISTRANTSINFO": [{}],
		"PAID": false
	},
	{
		"seatName": "I19",
		"REGISTRANTSINFO": [{}],
		"PAID": true
	},
	{
		"seatName": "I20",
		"REGISTRANTSINFO": [{}],
		"PAID": true
	},
	{
		"seatName": "I21",
		"REGISTRANTSINFO": [{}],
		"PAID": false
	},
	{
		"seatName": "I22",
		"REGISTRANTSINFO": [{}],
		"PAID": true
	},
	{
		"seatName": "I23",
		"REGISTRANTSINFO": [{}],
		"PAID": true
	},
	{
		"seatName": "I24",
		"REGISTRANTSINFO": [{}],
		"PAID": false
	},
	{
		"seatName": "I25",
		"REGISTRANTSINFO": [{}],
		"PAID": true
	},
	{
		"seatName": "I26",
		"REGISTRANTSINFO": [{}],
		"PAID": true
	},
	{
		"seatName": "I27",
		"REGISTRANTSINFO": [{}],
		"PAID": false
	},
	{
		"seatName": "I28",
		"REGISTRANTSINFO": [{}],
		"PAID": true
	},
	{
		"seatName": "I29",
		"REGISTRANTSINFO": [{}],
		"PAID": false
	},
	{
		"seatName": "I30",
		"REGISTRANTSINFO": [{}],
		"PAID": false
	},
	{
		"seatName": "I31",
		"REGISTRANTSINFO": [{}],
		"PAID": true
	},
	{
		"seatName": "I32",
		"REGISTRANTSINFO": [{}],
		"PAID": false
	},
	{
		"seatName": "I33",
		"REGISTRANTSINFO": [{}],
		"PAID": true
	},
	{
		"seatName": "I34",
		"REGISTRANTSINFO": [{}],
		"PAID": false
	},
	{
		"seatName": "I35",
		"REGISTRANTSINFO": [{}],
		"PAID": true
	},
	{
		"seatName": "I36",
		"REGISTRANTSINFO": [{}],
		"PAID": true
	},
	{
		"seatName": "I37",
		"REGISTRANTSINFO": [{}],
		"PAID": true
	},
	{
		"seatName": "I38",
		"REGISTRANTSINFO": [{}],
		"PAID": false
	},
	{
		"seatName": "I39",
		"REGISTRANTSINFO": [{}],
		"PAID": true
	},
	{
		"seatName": "I40",
		"REGISTRANTSINFO": [{}],
		"PAID": false
	},
	{
		"seatName": "I41",
		"REGISTRANTSINFO": [{}],
		"PAID": false
	},
	{
		"seatName": "I42",
		"REGISTRANTSINFO": [{}],
		"PAID": false
	},
	{
		"seatName": "I43",
		"REGISTRANTSINFO": [{}],
		"PAID": false
	},
	{
		"seatName": "I44",
		"REGISTRANTSINFO": [{}],
		"PAID": true
	},
	{
		"seatName": "I45",
		"REGISTRANTSINFO": [{}],
		"PAID": false
	},
	{
		"seatName": "I46",
		"REGISTRANTSINFO": [{}],
		"PAID": false
	},
	{
		"seatName": "I47",
		"REGISTRANTSINFO": [{}],
		"PAID": true
	},
	{
		"seatName": "I48",
		"REGISTRANTSINFO": [{}],
		"PAID": true
	},
	{
		"seatName": "I49",
		"REGISTRANTSINFO": [{}],
		"PAID": true
	},
	{
		"seatName": "I50",
		"REGISTRANTSINFO": [{}],
		"PAID": true
	},
	{
		"seatName": "J10",
		"REGISTRANTSINFO": [{}],
		"PAID": true
	},
	{
		"seatName": "J11",
		"REGISTRANTSINFO": [{}],
		"PAID": false
	},
	{
		"seatName": "J12",
		"REGISTRANTSINFO": [{}],
		"PAID": true
	},
	{
		"seatName": "J13",
		"REGISTRANTSINFO": [{}],
		"PAID": false
	},
	{
		"seatName": "J14",
		"REGISTRANTSINFO": [{}],
		"PAID": true
	},
	{
		"seatName": "J15",
		"REGISTRANTSINFO": [{}],
		"PAID": true
	},
	{
		"seatName": "J16",
		"REGISTRANTSINFO": [{}],
		"PAID": false
	},
	{
		"seatName": "J17",
		"REGISTRANTSINFO": [{}],
		"PAID": true
	},
	{
		"seatName": "J18",
		"REGISTRANTSINFO": [{}],
		"PAID": false
	},
	{
		"seatName": "J19",
		"REGISTRANTSINFO": [{}],
		"PAID": false
	},
	{
		"seatName": "J20",
		"REGISTRANTSINFO": [{}],
		"PAID": true
	},
	{
		"seatName": "J21",
		"REGISTRANTSINFO": [{}],
		"PAID": true
	},
	{
		"seatName": "J22",
		"REGISTRANTSINFO": [{}],
		"PAID": true
	},
	{
		"seatName": "J23",
		"REGISTRANTSINFO": [{}],
		"PAID": false
	},
	{
		"seatName": "J24",
		"REGISTRANTSINFO": [{}],
		"PAID": true
	},
	{
		"seatName": "J25",
		"REGISTRANTSINFO": [{}],
		"PAID": true
	},
	{
		"seatName": "J26",
		"REGISTRANTSINFO": [{}],
		"PAID": true
	},
	{
		"seatName": "J27",
		"REGISTRANTSINFO": [{}],
		"PAID": true
	},
	{
		"seatName": "J28",
		"REGISTRANTSINFO": [{}],
		"PAID": false
	},
	{
		"seatName": "J29",
		"REGISTRANTSINFO": [{}],
		"PAID": false
	},
	{
		"seatName": "J30",
		"REGISTRANTSINFO": [{}],
		"PAID": false
	},
	{
		"seatName": "J31",
		"REGISTRANTSINFO": [{}],
		"PAID": false
	},
	{
		"seatName": "J32",
		"REGISTRANTSINFO": [{}],
		"PAID": false
	},
	{
		"seatName": "J33",
		"REGISTRANTSINFO": [{}],
		"PAID": true
	},
	{
		"seatName": "J34",
		"REGISTRANTSINFO": [{}],
		"PAID": true
	},
	{
		"seatName": "J35",
		"REGISTRANTSINFO": [{}],
		"PAID": true
	},
	{
		"seatName": "J36",
		"REGISTRANTSINFO": [{}],
		"PAID": true
	},
	{
		"seatName": "J37",
		"REGISTRANTSINFO": [{}],
		"PAID": false
	},
	{
		"seatName": "J38",
		"REGISTRANTSINFO": [{}],
		"PAID": false
	},
	{
		"seatName": "J39",
		"REGISTRANTSINFO": [{}],
		"PAID": true
	},
	{
		"seatName": "J40",
		"REGISTRANTSINFO": [{}],
		"PAID": false
	},
	{
		"seatName": "J41",
		"REGISTRANTSINFO": [{}],
		"PAID": false
	},
	{
		"seatName": "J42",
		"REGISTRANTSINFO": [{}],
		"PAID": false
	},
	{
		"seatName": "J43",
		"REGISTRANTSINFO": [{}],
		"PAID": false
	},
	{
		"seatName": "J44",
		"REGISTRANTSINFO": [{}],
		"PAID": false
	},
	{
		"seatName": "J45",
		"REGISTRANTSINFO": [{}],
		"PAID": true
	},
	{
		"seatName": "J46",
		"REGISTRANTSINFO": [{}],
		"PAID": false
	},
	{
		"seatName": "J47",
		"REGISTRANTSINFO": [{}],
		"PAID": false
	},
	{
		"seatName": "J48",
		"REGISTRANTSINFO": [{}],
		"PAID": false
	},
	{
		"seatName": "J49",
		"REGISTRANTSINFO": [{}],
		"PAID": true
	},
	{
		"seatName": "J50",
		"REGISTRANTSINFO": [{}],
		"PAID": true
	}
]
